phulpy/__init__.py
phulpy/__main__.py
phulpy/command.py
phulpy/file.py
phulpy/helpers.py
phulpy/output.py
phulpy/phulpy.py
phulpy/source.py
phulpy/version.py
phulpy-1.0.10.dist-info/METADATA
phulpy-1.0.10.dist-info/WHEEL
phulpy-1.0.10.dist-info/entry_points.txt
phulpy-1.0.10.dist-info/top_level.txt
phulpy-1.0.10.dist-info/RECORD
